<?xml version='1.0' encoding='utf-8'?>
<annotation verified="yes">
    <folder>Annotation</folder>
    <filename>dvs-video.mp4#t=14.533333.jpg</filename>
    <path>test-PascalVOC-export/Annotations/dvs-video.mp4#t=14.533333.jpg</path>
    <source>
        <database>Unknown</database>
    </source>
    <size>
        <width>346</width>
        <height>260</height>
        <depth>3</depth>
    </size>
    <segmented>0</segmented>
    <object>
    <name>object</name>
    <pose>Unspecified</pose>
    <truncated>0</truncated>
    <difficult>0</difficult>
    <bndbox>
        <xmin>149.88928627106083</xmin>
        <ymin>153.4784389989619</ymin>
        <xmax>175.49685942080265</xmax>
        <ymax>165.78847494048898</ymax>
    </bndbox>
</object>
</annotation>