<annotation verified="yes">
    <folder>Annotation</folder>
    <filename>2.mp4#t=69.733333.jpg</filename>
    <path>paowu-PascalVOC-export/Annotations/2.mp4#t=69.733333.jpg</path>
    <source>
        <database>Unknown</database>
    </source>
    <size>
        <width>346</width>
        <height>260</height>
        <depth>3</depth>
    </size>
    <segmented>0</segmented>
    <object>
    <name>object</name>
    <pose>Unspecified</pose>
    <truncated>0</truncated>
    <difficult>0</difficult>
    <bndbox>
        <xmin>222.80753189401372</xmin>
        <ymin>87.57180156657962</ymin>
        <xmax>230.0512486870553</xmax>
        <ymax>97.07571801566579</ymax>
    </bndbox>
</object>
</annotation>
