<annotation verified="yes">
    <folder>Annotation</folder>
    <filename>3.mp4#t=42.2.jpg</filename>
    <path>paowu-PascalVOC-export/Annotations/3.mp4#t=42.2.jpg</path>
    <source>
        <database>Unknown</database>
    </source>
    <size>
        <width>346</width>
        <height>260</height>
        <depth>3</depth>
    </size>
    <segmented>0</segmented>
    <object>
    <name>object</name>
    <pose>Unspecified</pose>
    <truncated>0</truncated>
    <difficult>0</difficult>
    <bndbox>
        <xmin>102.83370824931764</xmin>
        <ymin>221.07921311500488</ymin>
        <xmax>106.22919401968073</xmax>
        <ymax>237.59791122715401</ymax>
    </bndbox>
</object>
</annotation>
