<annotation verified="yes">
    <folder>Annotation</folder>
    <filename>frame0199-timestamp7.9634.bmp</filename>
    <path>paowu3-PascalVOC-export/Annotations/frame0199-timestamp7.9634.bmp</path>
    <source>
        <database>Unknown</database>
    </source>
    <size>
        <width>346</width>
        <height>260</height>
        <depth>3</depth>
    </size>
    <segmented>0</segmented>
    <object>
    <name>object</name>
    <pose>Unspecified</pose>
    <truncated>0</truncated>
    <difficult>0</difficult>
    <bndbox>
        <xmin>60.168142115203025</xmin>
        <ymin>187.05193294352625</ymin>
        <xmax>70.62328847969783</xmax>
        <ymax>216.44891786814938</ymax>
    </bndbox>
</object>
</annotation>
