<annotation verified="yes">
    <folder>Annotation</folder>
    <filename>81ckd-1w1j1.mp4#t=119.3.jpg</filename>
    <path>bj-PascalVOC-export/Annotations/81ckd-1w1j1.mp4#t=119.3.jpg</path>
    <source>
        <database>Unknown</database>
    </source>
    <size>
        <width>346</width>
        <height>260</height>
        <depth>3</depth>
    </size>
    <segmented>0</segmented>
    <object>
    <name>object</name>
    <pose>Unspecified</pose>
    <truncated>0</truncated>
    <difficult>0</difficult>
    <bndbox>
        <xmin>277.6719126960193</xmin>
        <ymin>182.58426966292134</ymin>
        <xmax>288.3148560012063</xmax>
        <ymax>197.19101123595505</ymax>
    </bndbox>
</object>
</annotation>
