<annotation verified="yes">
    <folder>Annotation</folder>
    <filename>frame0347-timestamp13.8813.bmp</filename>
    <path>dvs2-PascalVOC-export/Annotations/frame0347-timestamp13.8813.bmp</path>
    <source>
        <database>Unknown</database>
    </source>
    <size>
        <width>346</width>
        <height>260</height>
        <depth>3</depth>
    </size>
    <segmented>0</segmented>
    <object>
    <name>object</name>
    <pose>Unspecified</pose>
    <truncated>0</truncated>
    <difficult>0</difficult>
    <bndbox>
        <xmin>170.3163767987599</xmin>
        <ymin>149.14728682170542</ymin>
        <xmax>180.10339842937555</xmax>
        <ymax>162.20008554384688</ymax>
    </bndbox>
</object>
</annotation>
