<annotation verified="yes">
    <folder>Annotation</folder>
    <filename>dvs-video.mp4#t=47.7.jpg</filename>
    <path>bj-PascalVOC-export/Annotations/dvs-video.mp4#t=47.7.jpg</path>
    <source>
        <database>Unknown</database>
    </source>
    <size>
        <width>346</width>
        <height>260</height>
        <depth>3</depth>
    </size>
    <segmented>0</segmented>
    <object>
    <name>object</name>
    <pose>Unspecified</pose>
    <truncated>0</truncated>
    <difficult>0</difficult>
    <bndbox>
        <xmin>137.97878713164602</xmin>
        <ymin>103.84116680761383</ymin>
        <xmax>142.34597620742457</xmax>
        <ymax>110.98893313063789</ymax>
    </bndbox>
</object>
</annotation>
