<annotation verified="yes">
    <folder>Annotation</folder>
    <filename>dvs-video2.mp4#t=19.9.jpg</filename>
    <path>bj-PascalVOC-export/Annotations/dvs-video2.mp4#t=19.9.jpg</path>
    <source>
        <database>Unknown</database>
    </source>
    <size>
        <width>346</width>
        <height>260</height>
        <depth>3</depth>
    </size>
    <segmented>0</segmented>
    <object>
    <name>object</name>
    <pose>Unspecified</pose>
    <truncated>0</truncated>
    <difficult>0</difficult>
    <bndbox>
        <xmin>141.55193687347045</xmin>
        <ymin>178.4956211295461</ymin>
        <xmax>147.50718644317786</xmax>
        <ymax>184.45209306539948</ymax>
    </bndbox>
</object>
</annotation>
