<annotation verified="yes">
    <folder>Annotation</folder>
    <filename>dvs-video.mp4#t=82.5.jpg</filename>
    <path>bj-PascalVOC-export/Annotations/dvs-video.mp4#t=82.5.jpg</path>
    <source>
        <database>Unknown</database>
    </source>
    <size>
        <width>346</width>
        <height>260</height>
        <depth>3</depth>
    </size>
    <segmented>0</segmented>
    <object>
    <name>object</name>
    <pose>Unspecified</pose>
    <truncated>0</truncated>
    <difficult>0</difficult>
    <bndbox>
        <xmin>143.53702612136607</xmin>
        <ymin>119.12943871706759</ymin>
        <xmax>149.49227569107347</xmax>
        <ymax>125.08591065292097</ymax>
    </bndbox>
</object>
</annotation>
