<annotation verified="yes">
    <folder>Annotation</folder>
    <filename>dvs-video2.mp4#t=168.7.jpg</filename>
    <path>bj-PascalVOC-export/Annotations/dvs-video2.mp4#t=168.7.jpg</path>
    <source>
        <database>Unknown</database>
    </source>
    <size>
        <width>346</width>
        <height>260</height>
        <depth>3</depth>
    </size>
    <segmented>0</segmented>
    <object>
    <name>object</name>
    <pose>Unspecified</pose>
    <truncated>0</truncated>
    <difficult>0</difficult>
    <bndbox>
        <xmin>123.48769196134427</xmin>
        <ymin>46.65903167899395</ymin>
        <xmax>135.1996767237757</xmax>
        <ymax>61.3516609392898</ymax>
    </bndbox>
</object>
</annotation>
