<annotation verified="yes">
    <folder>Annotation</folder>
    <filename>dvs-video3.mp4#t=139.5.jpg</filename>
    <path>bj-PascalVOC-export/Annotations/dvs-video3.mp4#t=139.5.jpg</path>
    <source>
        <database>Unknown</database>
    </source>
    <size>
        <width>346</width>
        <height>260</height>
        <depth>3</depth>
    </size>
    <segmented>0</segmented>
    <object>
    <name>object</name>
    <pose>Unspecified</pose>
    <truncated>0</truncated>
    <difficult>0</difficult>
    <bndbox>
        <xmin>115.15034256375391</xmin>
        <ymin>59.16762728871349</ymin>
        <xmax>129.83995211103903</xmax>
        <ymax>73.06605877608641</ymax>
    </bndbox>
</object>
</annotation>
