<annotation verified="yes">
    <folder>Annotation</folder>
    <filename>1.mp4#t=13.65.jpg</filename>
    <path>v2e-PascalVOC-export/Annotations/1.mp4#t=13.65.jpg</path>
    <source>
        <database>Unknown</database>
    </source>
    <size>
        <width>346</width>
        <height>260</height>
        <depth>3</depth>
    </size>
    <segmented>0</segmented>
    <object>
    <name>object</name>
    <pose>Unspecified</pose>
    <truncated>0</truncated>
    <difficult>0</difficult>
    <bndbox>
        <xmin>83.73640108354736</xmin>
        <ymin>117.14395110140141</ymin>
        <xmax>90.68418619021287</xmax>
        <ymax>124.8873646180108</ymax>
    </bndbox>
</object>
</annotation>
