<annotation verified="yes">
    <folder>Annotation</folder>
    <filename>2.mp4#t=121.6.jpg</filename>
    <path>v2e-PascalVOC-export/Annotations/2.mp4#t=121.6.jpg</path>
    <source>
        <database>Unknown</database>
    </source>
    <size>
        <width>346</width>
        <height>260</height>
        <depth>3</depth>
    </size>
    <segmented>0</segmented>
    <object>
    <name>object</name>
    <pose>Unspecified</pose>
    <truncated>0</truncated>
    <difficult>0</difficult>
    <bndbox>
        <xmin>303.6836064087545</xmin>
        <ymin>94.31081171024843</ymin>
        <xmax>312.02095580634483</xmax>
        <ymax>104.83390607101947</ymax>
    </bndbox>
</object>
</annotation>
