<annotation verified="yes">
    <folder>Annotation</folder>
    <filename>3.mp4#t=83.25.jpg</filename>
    <path>v2e-PascalVOC-export/Annotations/3.mp4#t=83.25.jpg</path>
    <source>
        <database>Unknown</database>
    </source>
    <size>
        <width>346</width>
        <height>260</height>
        <depth>3</depth>
    </size>
    <segmented>0</segmented>
    <object>
    <name>object</name>
    <pose>Unspecified</pose>
    <truncated>0</truncated>
    <difficult>0</difficult>
    <bndbox>
        <xmin>216.9354770680098</xmin>
        <ymin>199.1447177812679</ymin>
        <xmax>223.6847659716713</xmax>
        <ymax>208.6750728786333</ymax>
    </bndbox>
</object>
</annotation>
