<annotation verified="yes">
    <folder>Annotation</folder>
    <filename>4.mp4#t=146.35.jpg</filename>
    <path>v2e-PascalVOC-export/Annotations/4.mp4#t=146.35.jpg</path>
    <source>
        <database>Unknown</database>
    </source>
    <size>
        <width>346</width>
        <height>260</height>
        <depth>3</depth>
    </size>
    <segmented>0</segmented>
    <object>
    <name>object</name>
    <pose>Unspecified</pose>
    <truncated>0</truncated>
    <difficult>0</difficult>
    <bndbox>
        <xmin>177.8293442849243</xmin>
        <ymin>76.63994193759844</ymin>
        <xmax>183.38756510066494</xmax>
        <ymax>84.97900264779317</ymax>
    </bndbox>
</object>
</annotation>
