<annotation verified="yes">
    <folder>Annotation</folder>
    <filename>4.mp4#t=146.7.jpg</filename>
    <path>v2e-PascalVOC-export/Annotations/4.mp4#t=146.7.jpg</path>
    <source>
        <database>Unknown</database>
    </source>
    <size>
        <width>346</width>
        <height>260</height>
        <depth>3</depth>
    </size>
    <segmented>0</segmented>
    <object>
    <name>object</name>
    <pose>Unspecified</pose>
    <truncated>0</truncated>
    <difficult>0</difficult>
    <bndbox>
        <xmin>178.22635486491166</xmin>
        <ymin>78.62542955326461</ymin>
        <xmax>183.58607947764833</xmax>
        <ymax>88.35433977439504</ymax>
    </bndbox>
</object>
</annotation>
