<annotation verified="yes">
    <folder>Annotation</folder>
    <filename>5.mp4#t=2.5.jpg</filename>
    <path>v2e-PascalVOC-export/Annotations/5.mp4#t=2.5.jpg</path>
    <source>
        <database>Unknown</database>
    </source>
    <size>
        <width>346</width>
        <height>260</height>
        <depth>3</depth>
    </size>
    <segmented>0</segmented>
    <object>
    <name>object</name>
    <pose>Unspecified</pose>
    <truncated>0</truncated>
    <difficult>0</difficult>
    <bndbox>
        <xmin>149.44264255333277</xmin>
        <ymin>53.01260022909507</ymin>
        <xmax>155.19939592003618</xmax>
        <ymax>63.138602520045815</ymax>
    </bndbox>
</object>
</annotation>
