<annotation verified="yes">
    <folder>Annotation</folder>
    <filename>5.mp4#t=8.45.jpg</filename>
    <path>v2e-PascalVOC-export/Annotations/5.mp4#t=8.45.jpg</path>
    <source>
        <database>Unknown</database>
    </source>
    <size>
        <width>346</width>
        <height>260</height>
        <depth>3</depth>
    </size>
    <segmented>0</segmented>
    <object>
    <name>object</name>
    <pose>Unspecified</pose>
    <truncated>0</truncated>
    <difficult>0</difficult>
    <bndbox>
        <xmin>124.2320981575577</xmin>
        <ymin>114.76136232706007</ymin>
        <xmax>131.1798832642232</xmax>
        <ymax>124.68881858310067</ymax>
    </bndbox>
</object>
</annotation>
