<annotation verified="yes">
    <folder>Annotation</folder>
    <filename>5.mp4#t=30.1.jpg</filename>
    <path>v2e-PascalVOC-export/Annotations/5.mp4#t=30.1.jpg</path>
    <source>
        <database>Unknown</database>
    </source>
    <size>
        <width>346</width>
        <height>260</height>
        <depth>3</depth>
    </size>
    <segmented>0</segmented>
    <object>
    <name>object</name>
    <pose>Unspecified</pose>
    <truncated>0</truncated>
    <difficult>0</difficult>
    <bndbox>
        <xmin>120.65894841573325</xmin>
        <ymin>153.27988387519687</ymin>
        <xmax>126.41568360845727</xmax>
        <ymax>164.00153335973295</ymax>
    </bndbox>
</object>
</annotation>
